LICENSE
README.md
setup.py
gptzero/__init__.py
gptzero/api.py
gptzero.egg-info/PKG-INFO
gptzero.egg-info/SOURCES.txt
gptzero.egg-info/dependency_links.txt
gptzero.egg-info/requires.txt
gptzero.egg-info/top_level.txt