Metadata-Version: 2.1
Name: gptzero
Version: 0.1.2
Summary: Asynchronous Python wrapper for the GPTZero API
Home-page: https://github.com/Haste171/gptzero/
Author: David Peterson
Author-email: dapanon@proton.me
Classifier: Development Status :: 3 - Alpha
Classifier: Intended Audience :: Developers
Classifier: License :: OSI Approved :: MIT License
Classifier: Programming Language :: Python :: 3
Classifier: Programming Language :: Python :: 3.6
Classifier: Programming Language :: Python :: 3.7
Classifier: Programming Language :: Python :: 3.8
Classifier: Programming Language :: Python :: 3.9
Classifier: Programming Language :: Python :: 3.10
Classifier: Programming Language :: Python :: 3.11
License-File: LICENSE
